{
    "content": "\n677\u2028LACK OF ACCRETION\nIf no accretion takes place, the portion of the missing heir shall devolve to the legitimate heirs, and the portion of the missing legatee shall go to the benefit of the honoree.\nThe legitimate heirs and the honored person shall succeed to the obligations that were incumbent on the missing heir or legatee, except in the case of obligations of a personal nature.\nThe preceding provisions shall also apply in the case of termination of testamentary dispositions due to non-performance of the obligation.\n\n",
    "metadata": {
        "civil_codes_used": "Art. 677",
        "law": "Inheritance",
        "type": "ITALY"
    }
}